pararam_nexus_mcp/__init__.py
pararam_nexus_mcp/auth.py
pararam_nexus_mcp/captcha.py
pararam_nexus_mcp/client.py
pararam_nexus_mcp/config.py
pararam_nexus_mcp/helpers.py
pararam_nexus_mcp/models.py
pararam_nexus_mcp/schemas.py
pararam_nexus_mcp/server.py
pararam_nexus_mcp/tools/__init__.py
pararam_nexus_mcp/tools/chats.py
pararam_nexus_mcp/tools/posts.py
pararam_nexus_mcp/tools/users.py
pararam_nexus_mcp-0.1.0.dist-info/METADATA
pararam_nexus_mcp-0.1.0.dist-info/WHEEL
pararam_nexus_mcp-0.1.0.dist-info/entry_points.txt
pararam_nexus_mcp-0.1.0.dist-info/licenses/LICENSE
pararam_nexus_mcp-0.1.0.dist-info/RECORD
