Metadata-Version: 2.4
Name: pararam-nexus-mcp
Version: 0.1.0
Summary: Model Context Protocol server for pararam.io - a modern communication and collaboration platform
Project-URL: Homepage, https://github.com/ivolnistov/pararam-nexus-mcp
Project-URL: Repository, https://github.com/ivolnistov/pararam-nexus-mcp
Project-URL: Issues, https://github.com/ivolnistov/pararam-nexus-mcp/issues
Author-email: Ilya Volnistov <i.volnistov@gmail.com>
License: MIT
License-File: LICENSE
Keywords: async,communication,fastmcp,mcp,messaging,pararam,pararam.io
Classifier: Development Status :: 3 - Alpha
Classifier: Framework :: AsyncIO
Classifier: Intended Audience :: Developers
Classifier: License :: OSI Approved :: MIT License
Classifier: Programming Language :: Python :: 3
Classifier: Programming Language :: Python :: 3.13
Classifier: Topic :: Communications :: Chat
Classifier: Topic :: Software Development :: Libraries
Requires-Python: >=3.13
Requires-Dist: fastmcp>=0.1.0
Requires-Dist: httpx>=0.24.0
Requires-Dist: pararamio-aio==3.0.6
Requires-Dist: pydantic>=2.0.0
